{
  "version": "7",
  "dialect": "postgresql",
  "entries": [
    {
      "idx": 0,
      "version": "7",
      "when": 1776905836070,
      "tag": "0000_absurd_alex_wilder",
      "breakpoints": true
    },
    {
      "idx": 1,
      "version": "7",
      "when": 1776927436472,
      "tag": "0001_redundant_ulik",
      "breakpoints": true
    },
    {
      "idx": 2,
      "version": "7",
      "when": 1778581428575,
      "tag": "0002_strong_anita_blake",
      "breakpoints": true
    }
  ]
}