{"nodes": [{"id": "users_adems_projects_findash_src_app_dashboard_investments_page_tsx", "label": "page.tsx", "file_type": "code", "source_file": "/Users/adems/projects/findash/src/app/(dashboard)/investments/page.tsx", "source_location": "L1"}, {"id": "page_investmentspage", "label": "InvestmentsPage()", "file_type": "code", "source_file": "/Users/adems/projects/findash/src/app/(dashboard)/investments/page.tsx", "source_location": "L10"}], "edges": [{"source": "users_adems_projects_findash_src_app_dashboard_investments_page_tsx", "target": "refreshbutton", "relation": "imports_from", "confidence": "EXTRACTED", "source_file": "/Users/adems/projects/findash/src/app/(dashboard)/investments/page.tsx", "source_location": "L1", "weight": 1.0}, {"source": "users_adems_projects_findash_src_app_dashboard_investments_page_tsx", "target": "holdingstable", "relation": "imports_from", "confidence": "EXTRACTED", "source_file": "/Users/adems/projects/findash/src/app/(dashboard)/investments/page.tsx", "source_location": "L2", "weight": 1.0}, {"source": "users_adems_projects_findash_src_app_dashboard_investments_page_tsx", "target": "spendingdonut", "relation": "imports_from", "confidence": "EXTRACTED", "source_file": "/Users/adems/projects/findash/src/app/(dashboard)/investments/page.tsx", "source_location": "L3", "weight": 1.0}, {"source": "users_adems_projects_findash_src_app_dashboard_investments_page_tsx", "target": "statcard", "relation": "imports_from", "confidence": "EXTRACTED", "source_file": "/Users/adems/projects/findash/src/app/(dashboard)/investments/page.tsx", "source_location": "L4", "weight": 1.0}, {"source": "users_adems_projects_findash_src_app_dashboard_investments_page_tsx", "target": "monthselector", "relation": "imports_from", "confidence": "EXTRACTED", "source_file": "/Users/adems/projects/findash/src/app/(dashboard)/investments/page.tsx", "source_location": "L5", "weight": 1.0}, {"source": "users_adems_projects_findash_src_app_dashboard_investments_page_tsx", "target": "transactions", "relation": "imports_from", "confidence": "EXTRACTED", "source_file": "/Users/adems/projects/findash/src/app/(dashboard)/investments/page.tsx", "source_location": "L6", "weight": 1.0}, {"source": "users_adems_projects_findash_src_app_dashboard_investments_page_tsx", "target": "data", "relation": "imports_from", "confidence": "EXTRACTED", "source_file": "/Users/adems/projects/findash/src/app/(dashboard)/investments/page.tsx", "source_location": "L7", "weight": 1.0}, {"source": "users_adems_projects_findash_src_app_dashboard_investments_page_tsx", "target": "prices", "relation": "imports_from", "confidence": "EXTRACTED", "source_file": "/Users/adems/projects/findash/src/app/(dashboard)/investments/page.tsx", "source_location": "L8", "weight": 1.0}, {"source": "users_adems_projects_findash_src_app_dashboard_investments_page_tsx", "target": "page_investmentspage", "relation": "contains", "confidence": "EXTRACTED", "source_file": "/Users/adems/projects/findash/src/app/(dashboard)/investments/page.tsx", "source_location": "L10", "weight": 1.0}], "raw_calls": [{"caller_nid": "page_investmentspage", "callee": "getTransactions", "source_file": "/Users/adems/projects/findash/src/app/(dashboard)/investments/page.tsx", "source_location": "L16"}, {"caller_nid": "page_investmentspage", "callee": "getAvailableMonths", "source_file": "/Users/adems/projects/findash/src/app/(dashboard)/investments/page.tsx", "source_location": "L18"}, {"caller_nid": "page_investmentspage", "callee": "getInvestmentHoldings", "source_file": "/Users/adems/projects/findash/src/app/(dashboard)/investments/page.tsx", "source_location": "L19"}, {"caller_nid": "page_investmentspage", "callee": "reduce", "source_file": "/Users/adems/projects/findash/src/app/(dashboard)/investments/page.tsx", "source_location": "L20"}, {"caller_nid": "page_investmentspage", "callee": "reduce", "source_file": "/Users/adems/projects/findash/src/app/(dashboard)/investments/page.tsx", "source_location": "L23"}, {"caller_nid": "page_investmentspage", "callee": "filter", "source_file": "/Users/adems/projects/findash/src/app/(dashboard)/investments/page.tsx", "source_location": "L23"}, {"caller_nid": "page_investmentspage", "callee": "filterByMonth", "source_file": "/Users/adems/projects/findash/src/app/(dashboard)/investments/page.tsx", "source_location": "L23"}, {"caller_nid": "page_investmentspage", "callee": "map", "source_file": "/Users/adems/projects/findash/src/app/(dashboard)/investments/page.tsx", "source_location": "L28"}, {"caller_nid": "page_investmentspage", "callee": "getLivePrices", "source_file": "/Users/adems/projects/findash/src/app/(dashboard)/investments/page.tsx", "source_location": "L29"}, {"caller_nid": "page_investmentspage", "callee": "map", "source_file": "/Users/adems/projects/findash/src/app/(dashboard)/investments/page.tsx", "source_location": "L31"}, {"caller_nid": "page_investmentspage", "callee": "every", "source_file": "/Users/adems/projects/findash/src/app/(dashboard)/investments/page.tsx", "source_location": "L39"}, {"caller_nid": "page_investmentspage", "callee": "reduce", "source_file": "/Users/adems/projects/findash/src/app/(dashboard)/investments/page.tsx", "source_location": "L40"}, {"caller_nid": "page_investmentspage", "callee": "map", "source_file": "/Users/adems/projects/findash/src/app/(dashboard)/investments/page.tsx", "source_location": "L47"}, {"caller_nid": "page_investmentspage", "callee": "toLocaleString", "source_file": "/Users/adems/projects/findash/src/app/(dashboard)/investments/page.tsx", "source_location": "L50"}, {"caller_nid": "page_investmentspage", "callee": "abs", "source_file": "/Users/adems/projects/findash/src/app/(dashboard)/investments/page.tsx", "source_location": "L50"}, {"caller_nid": "page_investmentspage", "callee": "toFixed", "source_file": "/Users/adems/projects/findash/src/app/(dashboard)/investments/page.tsx", "source_location": "L50"}]}